{
  "hints": [],
  "groups": [
    {
      "sourceType": "com.aron.rabbitmq.RabbitProperties",
      "name": "rabbitmq",
      "type": "com.aron.rabbitmq.RabbitProperties"
    }
  ],
  "properties": [
    {
      "sourceType": "com.aron.rabbitmq.RabbitProperties",
      "name": "rabbitmq.addresses",
      "description": "Comma-separated list of addresses to which the client should connect.",
      "type": "java.lang.String"
    },
    {
      "sourceType": "com.aron.rabbitmq.RabbitProperties",
      "defaultValue": "60s",
      "name": "rabbitmq.connection-timeout",
      "description": "Connection timeout. Set it to zero to wait forever.",
      "type": "java.time.Duration"
    },
    {
      "sourceType": "com.aron.rabbitmq.RabbitProperties",
      "name": "rabbitmq.direct-exchange-name",
      "type": "java.lang.String"
    },
    {
      "sourceType": "com.aron.rabbitmq.RabbitProperties",
      "defaultValue": "localhost",
      "name": "rabbitmq.host",
      "description": "RabbitMQ host.",
      "type": "java.lang.String"
    },
    {
      "sourceType": "com.aron.rabbitmq.RabbitProperties",
      "defaultValue": "guest",
      "name": "rabbitmq.password",
      "description": "Login to authenticate against the broker.",
      "type": "java.lang.String"
    },
    {
      "sourceType": "com.aron.rabbitmq.RabbitProperties",
      "defaultValue": 5672,
      "name": "rabbitmq.port",
      "description": "RabbitMQ port.",
      "type": "java.lang.Integer"
    },
    {
      "sourceType": "com.aron.rabbitmq.RabbitProperties",
      "defaultValue": false,
      "name": "rabbitmq.publisher-confirms",
      "description": "Whether to enable publisher confirms.",
      "type": "java.lang.Boolean"
    },
    {
      "sourceType": "com.aron.rabbitmq.RabbitProperties",
      "defaultValue": false,
      "name": "rabbitmq.publisher-returns",
      "description": "Whether to enable publisher returns.",
      "type": "java.lang.Boolean"
    },
    {
      "sourceType": "com.aron.rabbitmq.RabbitProperties",
      "defaultValue": false,
      "name": "rabbitmq.reply-queue-auto-delete",
      "type": "java.lang.Boolean"
    },
    {
      "sourceType": "com.aron.rabbitmq.RabbitProperties",
      "defaultValue": false,
      "name": "rabbitmq.reply-queue-durable",
      "type": "java.lang.Boolean"
    },
    {
      "sourceType": "com.aron.rabbitmq.RabbitProperties",
      "defaultValue": false,
      "name": "rabbitmq.reply-queue-exclusive",
      "type": "java.lang.Boolean"
    },
    {
      "sourceType": "com.aron.rabbitmq.RabbitProperties",
      "name": "rabbitmq.reply-queue-name",
      "type": "java.lang.String"
    },
    {
      "sourceType": "com.aron.rabbitmq.RabbitProperties",
      "defaultValue": false,
      "name": "rabbitmq.request-queue-auto-delete",
      "type": "java.lang.Boolean"
    },
    {
      "sourceType": "com.aron.rabbitmq.RabbitProperties",
      "defaultValue": false,
      "name": "rabbitmq.request-queue-durable",
      "type": "java.lang.Boolean"
    },
    {
      "sourceType": "com.aron.rabbitmq.RabbitProperties",
      "defaultValue": false,
      "name": "rabbitmq.request-queue-exclusive",
      "type": "java.lang.Boolean"
    },
    {
      "sourceType": "com.aron.rabbitmq.RabbitProperties",
      "name": "rabbitmq.request-queue-name",
      "type": "java.lang.String"
    },
    {
      "sourceType": "com.aron.rabbitmq.RabbitProperties",
      "name": "rabbitmq.routing-key",
      "type": "java.lang.String"
    },
    {
      "sourceType": "com.aron.rabbitmq.RabbitProperties",
      "defaultValue": "guest",
      "name": "rabbitmq.username",
      "description": "Login user to authenticate to the broker.",
      "type": "java.lang.String"
    },
    {
      "sourceType": "com.aron.rabbitmq.RabbitProperties",
      "name": "rabbitmq.virtual-host",
      "description": "Virtual host to use when connecting to the broker.",
      "type": "java.lang.String"
    }
  ]
}